rasahub_humhub/__init__.py
rasahub_humhub/humhub.py
rasahub_humhub-0.3.1.dist-info/METADATA
rasahub_humhub-0.3.1.dist-info/RECORD
rasahub_humhub-0.3.1.dist-info/WHEEL
rasahub_humhub-0.3.1.dist-info/top_level.txt
